{
  "name": "promptkitty",
  "owner": {
    "name": "Baldaworks"
  },
  "metadata": {
    "description": "PromptKit assembly and agent instruction authoring for GitHub Copilot CLI.",
    "version": "0.4.2"
  },
  "plugins": [
    {
      "name": "promptkitty",
      "description": "Assemble PromptKit prompts and author provider-native agent instructions.",
      "version": "0.4.2",
      "source": "./plugins/promptkitty",
      "author": {
        "name": "Baldaworks",
        "url": "https://github.com/baldaworks"
      },
      "homepage": "https://github.com/baldaworks/promptkitty",
      "repository": "https://github.com/baldaworks/promptkitty",
      "license": "MIT",
      "keywords": ["promptkit", "prompts", "assembly", "cli"]
    }
  ]
}
